setup.py
elpylog/__init__.py
elpylog/handler.py
elpylog.egg-info/PKG-INFO
elpylog.egg-info/SOURCES.txt
elpylog.egg-info/dependency_links.txt
elpylog.egg-info/not-zip-safe
elpylog.egg-info/top_level.txt