Metadata-Version: 1.1
Name: elpylog
Version: 0.1.1
Summary: Python logger sending it's logs to elasticsearch.
Home-page: git@github.com:ondergetekende/elpylog.git
Author: Koert van der Veer
Author-email: opensource@ondergetekende.nl
License: BSD License
Download-URL: https://github.com/ondergetekende/elpylog/tarball/v0.1.0
Keywords: logging elasticsearch bulk udp logstash
Platform: UNKNOWN
